bioomics/__init__.py
bioomics/bio_dict.py
bioomics/bio_handler.py
bioomics/concurrency.py
bioomics/integrate_data.py
bioomics/mirbase.py
bioomics/rnacentral.py
bioomics/connector/__init__.py
bioomics/connector/conn_ftp.py
bioomics/connector/conn_ftplib.py
bioomics/connector/conn_http.py
bioomics/connector/conn_redis.py
bioomics/constants/IEDB.py
bioomics/immune/__init__.py
bioomics/immune/iedb.py
bioomics/immune/iedb_antigen.py
bioomics/immune/iedb_epitope.py
bioomics/ncbi/__init__.py
bioomics/ncbi/genBank.py
bioomics/ncbi/integrate.py
bioomics/ncbi/integrate_ncbi_protein.py
bioomics/ncbi/integrate_uniprotkb_protein.py
bioomics/ncbi/ncbi.py
bioomics/ncbi/parse_id.py
bioomics/ncbi/refseq.py
bioomics/protein/__init__.py
bioomics/protein/expasy.py
bioomics/protein/uniprot.py
bioomics/protein/uniprot_sprot.py
bioomics/protein/uniprot_trembl.py
pipelines/__init__.py
pipelines/app.py
pipelines/retrieve_epitopes.py
bioomics-0.2.9.dist-info/LICENSE
bioomics-0.2.9.dist-info/METADATA
bioomics-0.2.9.dist-info/WHEEL
bioomics-0.2.9.dist-info/top_level.txt
bioomics-0.2.9.dist-info/RECORD
