Metadata-Version: 2.1
Name: bioomics
Version: 0.2.9
Summary: Download, retrieve and process omics data for further bioinformatics
Home-page: https://github.com/Tiezhengyuan/bio_omics
Author: Tiezheng Yuan
Author-email: tiezhengyuan@hotmail.com
Keywords: pypi,cicd,python
Classifier: Development Status :: 1 - Planning
Classifier: Intended Audience :: Developers
Classifier: Programming Language :: Python :: 3
Classifier: Operating System :: Unix
Classifier: Operating System :: MacOS :: MacOS X
Classifier: Operating System :: Microsoft :: Windows
License-File: LICENSE
Requires-Dist: Bio
Requires-Dist: biosequtils
Requires-Dist: lxml
Requires-Dist: redis
Requires-Dist: sh
